odoo8_addon_stock_account_quant_merge-8.0.1.0.0-py2.7-nspkg.pth
odoo_addons/stock_account_quant_merge/__openerp__.py
odoo_addons/stock_account_quant_merge/__init__.py
odoo_addons/stock_account_quant_merge/README.rst
odoo_addons/stock_account_quant_merge/models/stock.py
odoo_addons/stock_account_quant_merge/models/__init__.py
odoo_addons/stock_account_quant_merge/tests/__init__.py
odoo_addons/stock_account_quant_merge/tests/test_merge.py
odoo8_addon_stock_account_quant_merge-8.0.1.0.0.dist-info/top_level.txt
odoo8_addon_stock_account_quant_merge-8.0.1.0.0.dist-info/WHEEL
odoo8_addon_stock_account_quant_merge-8.0.1.0.0.dist-info/RECORD
odoo8_addon_stock_account_quant_merge-8.0.1.0.0.dist-info/metadata.json
odoo8_addon_stock_account_quant_merge-8.0.1.0.0.dist-info/DESCRIPTION.rst
odoo8_addon_stock_account_quant_merge-8.0.1.0.0.dist-info/METADATA
odoo8_addon_stock_account_quant_merge-8.0.1.0.0.dist-info/namespace_packages.txt
